x_goals/__init__.py
x_goals/__main__.py
x_goals/app.py
x_goals/cli.py
x_goals/pricing_engine.py
x_goals/state.py
x_goals-0.0.2.dist-info/METADATA
x_goals-0.0.2.dist-info/RECORD
x_goals-0.0.2.dist-info/WHEEL
x_goals-0.0.2.dist-info/entry_points.txt
x_goals-0.0.2.dist-info/top_level.txt
