Metadata-Version: 2.1
Name: x-goals
Version: 0.0.2
Summary: X-Goals package. Generated with cookiercutter-pylibrary using the command line cookiecutter gh:ionelmc/cookiecutter-pylibrary
Home-page: https://github.com/DonRegan/x-goals
Author: Donough Regan
Author-email: donoughr@starsgroup.com
License: Apache Software License 2.0
Platform: UNKNOWN
Classifier: Development Status :: 5 - Production/Stable
Classifier: Intended Audience :: Developers
Classifier: License :: OSI Approved :: Apache Software License
Classifier: Operating System :: Unix
Classifier: Operating System :: POSIX
Classifier: Operating System :: Microsoft :: Windows
Classifier: Programming Language :: Python
Classifier: Programming Language :: Python :: 3
Classifier: Programming Language :: Python :: 3.5
Classifier: Topic :: Utilities
Requires-Dist: IPython
Requires-Dist: dash
Requires-Dist: dash-html-components
Requires-Dist: dash-core-components
Requires-Dist: matplotlib
Requires-Dist: scipy
Requires-Dist: seaborn
